snaut.py
snaut-1.1.0.dist-info/LICENSE
snaut-1.1.0.dist-info/METADATA
snaut-1.1.0.dist-info/WHEEL
snaut-1.1.0.dist-info/entry_points.txt
snaut-1.1.0.dist-info/top_level.txt
snaut-1.1.0.dist-info/RECORD
