Metadata-Version: 2.1
Name: snaut
Version: 1.1.0
Summary: Artifact upload tool for Sonatype Nexus 3
Home-page: https://github.com/perewall/snaut
License: MIT
Platform: UNKNOWN
Classifier: Development Status :: 4 - Beta
Classifier: License :: OSI Approved :: MIT License
Classifier: Operating System :: OS Independent
Classifier: Programming Language :: Python :: 2
Classifier: Programming Language :: Python :: 2.7
Classifier: Programming Language :: Python :: 3
Classifier: Programming Language :: Python :: 3.4
Classifier: Programming Language :: Python :: 3.5
Classifier: Programming Language :: Python :: 3.6
Classifier: Programming Language :: Python :: 3.7
Classifier: Topic :: Software Development :: Libraries :: Python Modules
Requires-Dist: click (<8.0,>=7.0)
Requires-Dist: requests (<3.0,>=2.0)
Requires-Dist: python-dotenv (<1.0,>=0.10)
